{
  "players": [
    {
      "name": "Ronaldo",
      "number": 7,
      "position": "Forward",
      "club": "Al Nassr",
      "goals": 200,
      "photo": "https://b.fssta.com/uploads/application/soccer/headshots/885.vresize.350.350.medium.14.png",
      "id": 1
    },
    {
      "name": "Messi",
      "number": 30,
      "position": "Forward",
      "club": "Paris SG",
      "goals": 150,
      "photo": "https://b.fssta.com/uploads/application/soccer/headshots/711.vresize.350.350.medium.70.png",
      "id": 2
    },
    {
      "name": "Hazard",
      "number": 7,
      "position": "Forward",
      "club": "Real Madrid",
      "goals": 0,
      "photo": "https://b.fssta.com/uploads/application/soccer/headshots/215.vresize.350.350.medium.52.png",
      "id": 3
    },
    {
      "name": "De Bruyne",
      "number": 17,
      "position": "Midfielder",
      "club": "Manchester City",
      "goals": 8,
      "photo": "https://b.fssta.com/uploads/application/soccer/headshots/2342.vresize.350.350.medium.24.png",
      "id": 4
    },
    {
      "name": "Sergio Ramos",
      "number": 4,
      "position": "Defender",
      "club": "Paris SG",
      "goals": 3,
      "photo": "https://b.fssta.com/uploads/application/soccer/headshots/884.vresize.350.350.medium.61.png",
      "id": 5
    },
    {
      "name": "Haaland",
      "number": 9,
      "position": "Forward",
      "club": "Manchester City",
      "goals": 99,
      "photo": "https://b.fssta.com/uploads/application/soccer/headshots/66617.vresize.350.350.medium.77.png",
      "id": 6
    },
    {
      "name": "Neymar",
      "number": 10,
      "position": "Forward",
      "club": "Paris SG",
      "goals": 21,
      "photo": "https://b.fssta.com/uploads/application/soccer/headshots/713.vresize.350.350.medium.34.png",
      "id": 7
    },
    {
      "id": 8,
      "name": "Mbappe",
      "number": 7,
      "position": "Forward",
      "club": "Paris SG",
      "goals": 32,
      "photo": "https://b.fssta.com/uploads/application/soccer/headshots/40670.vresize.350.350.medium.91.png"
    },
    {
      "name": "Salah",
      "number": 11,
      "position": "Forward",
      "club": "Liverpool",
      "goals": 19,
      "photo": "https://b.fssta.com/uploads/application/soccer/headshots/224.vresize.350.350.medium.68.png",
      "id": 9
    },
    {
      "name": "Bruno Fernandes",
      "number": 8,
      "position": "Midfielder",
      "club": "Manchester United",
      "goals": 9,
      "photo": "https://b.fssta.com/uploads/application/soccer/headshots/1593.vresize.350.350.medium.21.png",
      "id": 10
    },
    {
      "name": "Lewandowski",
      "number": 9,
      "position": "Forward",
      "club": "Barcelona",
      "goals": 110,
      "photo": "https://b.fssta.com/uploads/application/soccer/headshots/2100.vresize.350.350.medium.55.png",
      "id": 11
    },
    {
      "name": "Benzema",
      "number": "9",
      "position": "Forward",
      "club": "Real Madrid",
      "goals": "96",
      "photo": "https://b.fssta.com/uploads/application/soccer/headshots/864.vresize.350.350.medium.48.png",
      "id": 12
    },
    {
      "name": "Odegaard",
      "number": 8,
      "position": "Midfielder",
      "club": "Arsenal",
      "goals": 5,
      "photo": "https://b.fssta.com/uploads/application/soccer/headshots/29113.vresize.350.350.medium.58.png",
      "id": 13
    },
    {
      "name": "Kane",
      "number": 10,
      "position": "Forward",
      "club": "Tottenham",
      "goals": 87,
      "photo": "https://b.fssta.com/uploads/application/soccer/headshots/453.vresize.350.350.medium.69.png",
      "id": 14
    },
    {
      "name": "Ibrahimovic",
      "number": "11",
      "position": "Forward",
      "club": "AC Milan",
      "goals": "111",
      "photo": "https://b.fssta.com/uploads/application/soccer/headshots/4046.vresize.350.350.medium.75.png",
      "id": 15
    }
  ]
}